{
  "$schema": "http://json-schema.org/schema",
  "id": "ng add",
  "title": "ng add",
  "type": "object",
  "properties": {
    "path": {
      "type": "string",
      "format": "path",
      "description": "The path at which to create the component file, relative to the current workspace. Default is a folder with the same name as the component in the project root.",
      "visible": false
    },
    "project": {
      "type": "string",
      "description": "The name of the project.",
      "$default": {
        "$source": "projectName"
      }
    }
  },
  "required": []
}
